{
	"frames": [{
	    "name": "sprite-00",
	    "position": {
	      "x": 168,
	      "y": 625,
	      "w": 120,
	      "h": 100
	    }
	  },
	  {
	    "name": "sprite-01",
	    "position": {
	      "x": 167,
	      "y": 832,
	      "w": 120,
	      "h": 100
	    }
	  },
	  {
	    "name": "sprite-02",
	    "position": {
	      "x": 732,
	      "y": 155,
	      "w": 112,
	      "h": 100
	    }
	  },
	  {
	    "name": "sprite-03",
	    "position": {
	      "x": 845,
	      "y": 154,
	      "w": 111,
	      "h": 100
	    }
	  },
	  {
		"name": "sprite-04",
		"position": {
		  "x": 168,
		  "y": 515,
		  "w": 120,
		  "h": 110
		}
	      },
	  
	      {
		"name": "sprite-05",
		"position": {
		  "x": 168,
		  "y": 280,
		  "w": 127,
		  "h": 120
		}
	      },
	      {
		"name": "sprite-06",
		"position": {
		  "x": 168,
		  "y": 155,
		  "w": 120,
		  "h": 123
		}
	      }

	]
      }